libcpab/__init__.py
libcpab/cpab.py
libcpab/expm.py
libcpab/findcellidx.py
libcpab/interpolation.py
libcpab/tesselation.py
libcpab/transformer.py
libcpab-0.1.2.dist-info/licenses/LICENSE
libcpab-0.1.2.dist-info/METADATA
libcpab-0.1.2.dist-info/WHEEL
libcpab-0.1.2.dist-info/top_level.txt
libcpab-0.1.2.dist-info/RECORD
