Metadata-Version: 2.4
Name: libcpab
Version: 0.1.2
Summary: Maintained fork of libcpab for PyTorch
Author-email: Andrew Wang <andrew.wang@ed.ac.uk>, Nicki Skafte Detlefsen <nsde@dtu.dk>
License: MIT
Project-URL: Homepage, https://github.com/Andrewwango/libcpab
Project-URL: Source, https://github.com/Andrewwango/libcpab
Project-URL: Tracker, https://github.com/Andrewwango/libcpab/issues
Platform: any
Classifier: Development Status :: 4 - Beta
Classifier: Intended Audience :: Developers
Classifier: Intended Audience :: Science/Research
Classifier: License :: OSI Approved :: MIT License
Classifier: Operating System :: OS Independent
Classifier: Programming Language :: Python :: 3
Classifier: Topic :: Utilities
Classifier: Topic :: Scientific/Engineering
Classifier: Topic :: Software Development :: Libraries
Requires-Python: >=3.9
License-File: LICENSE
Requires-Dist: numpy
Requires-Dist: matplotlib
Requires-Dist: torch
Requires-Dist: scipy
Dynamic: license-file
